display_df/__init__.py
display_df/display_df.py
display_df-0.3.0.dist-info/licenses/LICENSE
display_df-0.3.0.dist-info/METADATA
display_df-0.3.0.dist-info/WHEEL
display_df-0.3.0.dist-info/top_level.txt
display_df-0.3.0.dist-info/RECORD
