Metadata-Version: 2.4
Name: display_df
Version: 0.3.0
Summary: An interactive Pandas DataFrame viewer that enables better-than-notepad viewing abilities in normal Python files 👀
Home-page: https://github.com/yourusername/display_df
Author: Your Name
Author-email: your.email@example.com
Classifier: Programming Language :: Python :: 3
Classifier: License :: OSI Approved :: MIT License
Classifier: Operating System :: OS Independent
Requires-Python: >=3.7
License-File: LICENSE
Requires-Dist: pandas
Requires-Dist: PyQt5
Dynamic: author
Dynamic: author-email
Dynamic: classifier
Dynamic: description
Dynamic: description-content-type
Dynamic: home-page
Dynamic: license-file
Dynamic: requires-dist
Dynamic: requires-python
Dynamic: summary
